setup.py
RAI/__init__.py
RAI/utils.py
RAI/actors/__init__.py
RAI/actors/anti_list_actor.py
RAI/actors/base_actor.py
RAI/actors/chat_bot.py
RAI/actors/google_searcher.py
RAI/actors/knowledge_base_searcher.py
RAI/actors/qagpt.py
RAI/actors/text_summarizer.py
RAI/actors/token_counter.py
RAI/api_pmc_requests/__init__.py
RAI/api_pmc_requests/api_requester.py
RAI/api_pmc_requests/pmc_models.py
RAI/chat/__init__.py
RAI/chat/chat.py
RAI/chat/chat_menu.py
RAI/chat/message.py
RAI/containers/__init__.py
RAI/containers/rdict.py
RAI/heuristics/__init__.py
RAI/heuristics/poll.py
RAI/heuristics/poll_generator.py
RAI/profile/__init__.py
RAI/profile/profile.py
RAI/storages/__init__.py
RAI/storages/actions.py
RAI/storages/base_storage.py
RAI/storages/diary.py
RAI/storages/media_storage.py
RAI/storages/user_data.py
redemption_ai.egg-info/PKG-INFO
redemption_ai.egg-info/SOURCES.txt
redemption_ai.egg-info/dependency_links.txt
redemption_ai.egg-info/requires.txt
redemption_ai.egg-info/top_level.txt