Metadata-Version: 2.1
Name: redemption-ai
Version: 0.0.6
Summary: AI-powered (OpenAI API) tools for chat-like interactions and personal AI assistance.
Author: Ausar686
Author-email: glebyushkov@mail.ru
Requires-Dist: numpy==1.25.2
Requires-Dist: pandas==2.1.0
Requires-Dist: requests==2.31.0
Requires-Dist: urllib3==2.0.4
